kucoin_universal_sdk/__init__.py
kucoin_universal_sdk/api/__init__.py
kucoin_universal_sdk/api/api_rest.py
kucoin_universal_sdk/api/api_ws.py
kucoin_universal_sdk/api/client.py
kucoin_universal_sdk/extension/__init__.py
kucoin_universal_sdk/generate/__init__.py
kucoin_universal_sdk/generate/version.py
kucoin_universal_sdk/generate/account/__init__.py
kucoin_universal_sdk/generate/account/account/__init__.py
kucoin_universal_sdk/generate/account/account/api_account.py
kucoin_universal_sdk/generate/account/account/api_account_test.py
kucoin_universal_sdk/generate/account/account/model_get_account_info_resp.py
kucoin_universal_sdk/generate/account/account/model_get_apikey_info_resp.py
kucoin_universal_sdk/generate/account/account/model_get_cross_margin_account_accounts.py
kucoin_universal_sdk/generate/account/account/model_get_cross_margin_account_req.py
kucoin_universal_sdk/generate/account/account/model_get_cross_margin_account_resp.py
kucoin_universal_sdk/generate/account/account/model_get_futures_account_req.py
kucoin_universal_sdk/generate/account/account/model_get_futures_account_resp.py
kucoin_universal_sdk/generate/account/account/model_get_futures_ledger_data_list.py
kucoin_universal_sdk/generate/account/account/model_get_futures_ledger_req.py
kucoin_universal_sdk/generate/account/account/model_get_futures_ledger_resp.py
kucoin_universal_sdk/generate/account/account/model_get_isolated_margin_account_assets.py
kucoin_universal_sdk/generate/account/account/model_get_isolated_margin_account_assets_base_asset.py
kucoin_universal_sdk/generate/account/account/model_get_isolated_margin_account_assets_quote_asset.py
kucoin_universal_sdk/generate/account/account/model_get_isolated_margin_account_detail_v1_base_asset.py
kucoin_universal_sdk/generate/account/account/model_get_isolated_margin_account_detail_v1_quote_asset.py
kucoin_universal_sdk/generate/account/account/model_get_isolated_margin_account_detail_v1_req.py
kucoin_universal_sdk-1.2.1.post1.dist-info/licenses/LICENSE
kucoin_universal_sdk-1.2.1.post1.dist-info/METADATA
kucoin_universal_sdk-1.2.1.post1.dist-info/WHEEL
kucoin_universal_sdk-1.2.1.post1.dist-info/top_level.txt
kucoin_universal_sdk-1.2.1.post1.dist-info/RECORD
